meditact/__init__.py
meditact/oracle.py
meditact/predictor.py
meditact/preprocessor.py
tests/__init__.py
tests/test.py
meditact_ashhyun-1.0.0.dist-info/LICENSE
meditact_ashhyun-1.0.0.dist-info/METADATA
meditact_ashhyun-1.0.0.dist-info/WHEEL
meditact_ashhyun-1.0.0.dist-info/top_level.txt
meditact_ashhyun-1.0.0.dist-info/RECORD
