Metadata-Version: 2.1
Name: meditact-ashhyun
Version: 1.0.0
Summary: A python package that helps classifying medical subjects
Home-page: https://github.com/osamhack2020/Infra_Meditact_Meditact
Author: ashhyun
Author-email: youkind98@gmail.com
License: UNKNOWN
Platform: UNKNOWN
Classifier: Programming Language :: Python :: 3
Classifier: License :: OSI Approved :: MIT License
Classifier: Operating System :: OS Independent
Requires-Python: >=3.6
